{
  "_class": "oval",
  "booleanOperation": -1,
  "clippingMaskMode": 0,
  "do_objectID": "C7151183-D63D-40DD-8AD7-9C2F85816771",
  "edited": false,
  "exportOptions": {
    "_class": "exportOptions",
    "exportFormats": [
    ],
    "includedLayerIds": [
    ],
    "layerOptions": 0,
    "shouldTrim": false
  },
  "frame": {
    "_class": "rect",
    "constrainProportions": true,
    "height": 27.33845896504181,
    "width": 27.6609294320136,
    "x": 72.86351524039978,
    "y": 0.2476817649823386
  },
  "hasClippingMask": false,
  "isClosed": true,
  "isFixedToViewport": false,
  "isFlippedHorizontal": false,
  "isFlippedVertical": false,
  "isLocked": false,
  "isVisible": true,
  "layerListExpandedType": 1,
  "name": "Oval",
  "nameIsFixed": false,
  "pointRadiusBehaviour": 1,
  "points": [
    {
      "_class": "curvePoint",
      "cornerRadius": 0,
      "curveFrom": "{0.77614237490000348, 0.99999999999999789}",
      "curveMode": 2,
      "curveTo": "{0.22385762510000101, 0.99999999999999789}",
      "hasCurveFrom": true,
      "hasCurveTo": true,
      "point": "{0.50000000000000222, 0.99999999999999789}"
    },
    {
      "_class": "curvePoint",
      "cornerRadius": 0,
      "curveFrom": "{1.0000000000000044, 0.22385762509999954}",
      "curveMode": 2,
      "curveTo": "{1.0000000000000044, 0.77614237489999838}",
      "hasCurveFrom": true,
      "hasCurveTo": true,
      "point": "{1.0000000000000044, 0.49999999999999895}"
    },
    {
      "_class": "curvePoint",
      "cornerRadius": 0,
      "curveFrom": "{0.22385762510000101, 0}",
      "curveMode": 2,
      "curveTo": "{0.77614237490000348, 0}",
      "hasCurveFrom": true,
      "hasCurveTo": true,
      "point": "{0.50000000000000222, 0}"
    },
    {
      "_class": "curvePoint",
      "cornerRadius": 0,
      "curveFrom": "{0, 0.77614237489999838}",
      "curveMode": 2,
      "curveTo": "{0, 0.22385762509999954}",
      "hasCurveFrom": true,
      "hasCurveTo": true,
      "point": "{0, 0.49999999999999895}"
    }
  ],
  "resizingConstraint": 63,
  "resizingType": 0,
  "rotation": 0,
  "shouldBreakMaskChain": false,
  "style": {
    "_class": "style",
    "borders": [
      {
        "_class": "border",
        "color": {
          "_class": "color",
          "alpha": 1,
          "blue": 0.592,
          "green": 0.592,
          "red": 0.592
        },
        "fillType": 0,
        "isEnabled": false,
        "position": 0,
        "thickness": 1
      }
    ],
    "endMarkerType": 0,
    "fills": [
      {
        "_class": "fill",
        "color": {
          "_class": "color",
          "alpha": 1,
          "blue": 0.0823529411764706,
          "green": 0.09803921568627451,
          "red": 0.0784313725490196
        },
        "fillType": 0,
        "isEnabled": true,
        "noiseIndex": 0,
        "noiseIntensity": 0,
        "patternFillType": 0,
        "patternTileScale": 1
      }
    ],
    "miterLimit": 10,
    "startMarkerType": 0,
    "windingRule": 1
  },
  "userInfo": {
    "com.animaapp.stc-sketch-plugin": {
      "kModelPropertiesKey": {
      }
    }
  }
}