{
  "_class": "shapePath",
  "booleanOperation": -1,
  "do_objectID": "B1FB7133-6D40-4E15-9C24-2A06E446FFE7",
  "edited": true,
  "exportOptions": {
    "_class": "exportOptions",
    "exportFormats": [
    ],
    "includedLayerIds": [
    ],
    "layerOptions": 0,
    "shouldTrim": false
  },
  "frame": {
    "_class": "rect",
    "constrainProportions": false,
    "height": 2.659999999999997,
    "width": 22.22499999999999,
    "x": 0,
    "y": 0
  },
  "isClosed": false,
  "isFixedToViewport": false,
  "isFlippedHorizontal": false,
  "isFlippedVertical": false,
  "isLocked": false,
  "isVisible": true,
  "layerListExpandedType": 0,
  "name": "Path",
  "nameIsFixed": false,
  "pointRadiusBehaviour": 1,
  "points": [
    {
      "_class": "curvePoint",
      "cornerRadius": 0,
      "curveFrom": "{0.99995500562429673, 0.77593984962405849}",
      "curveMode": 4,
      "curveTo": "{0.99995500562429673, 0.5}",
      "hasCurveFrom": true,
      "hasCurveTo": false,
      "point": "{0.99995500562429673, 0.5}"
    },
    {
      "_class": "curvePoint",
      "cornerRadius": 0,
      "curveFrom": "{0.22384701912260949, 1}",
      "curveMode": 2,
      "curveTo": "{0.77610798650168722, 1}",
      "hasCurveFrom": true,
      "hasCurveTo": true,
      "point": "{0.49997750281214837, 1}"
    },
    {
      "_class": "curvePoint",
      "cornerRadius": 0,
      "curveFrom": "{0, 0.22406015037594151}",
      "curveMode": 2,
      "curveTo": "{0, 0.77593984962405849}",
      "hasCurveFrom": true,
      "hasCurveTo": true,
      "point": "{0, 0.5}"
    },
    {
      "_class": "curvePoint",
      "cornerRadius": 0,
      "curveFrom": "{0.77615298087739049, 0}",
      "curveMode": 2,
      "curveTo": "{0.22389201349831273, 0}",
      "hasCurveFrom": true,
      "hasCurveTo": true,
      "point": "{0.50002249718785163, 0}"
    },
    {
      "_class": "curvePoint",
      "cornerRadius": 0,
      "curveFrom": "{1, 0.5}",
      "curveMode": 4,
      "curveTo": "{1, 0.22406015037594151}",
      "hasCurveFrom": false,
      "hasCurveTo": true,
      "point": "{1, 0.5}"
    }
  ],
  "resizingConstraint": 63,
  "resizingType": 0,
  "rotation": 0,
  "shouldBreakMaskChain": false
}